esmeralda/__init__.py
esmeralda/defaults.py
esmeralda/runner.py
esmeralda-0.5.1.dist-info/METADATA
esmeralda-0.5.1.dist-info/WHEEL
esmeralda-0.5.1.dist-info/licenses/COPYING
esmeralda-0.5.1.dist-info/RECORD
