Metadata-Version: 2.4
Name: esmeralda
Version: 0.5.1
Summary: Queue request handling with key/value peristence layer
Author-email: doubleO8 <wb008@hdm-stuttgart.de>
License-Expression: GPL-2.0-only
License-File: COPYING
Requires-Python: >=3.7.3
Requires-Dist: djali>=0.5.1
Requires-Dist: jinja2>=2.11.2
Requires-Dist: pendulum>=2.1.2
Requires-Dist: quasimodo>=0.8.0
